bosc/__init__.py
bosc/collection.py
bosc/database.py
bosc/document.py
bosc/encoder.py
bosc/fields.py
bosc/index.py
bosc/query/__init__.py
bosc/query/base.py
bosc/query/find/__init__.py
bosc/query/find/comparison.py
bosc/query/find/logical.py
bosc/query/update/__init__.py
bosc/query/update/values.py
bosc-0.0.7.dist-info/LICENSE
bosc-0.0.7.dist-info/WHEEL
bosc-0.0.7.dist-info/METADATA
bosc-0.0.7.dist-info/RECORD
