Metadata-Version: 2.1
Name: bosc
Version: 0.0.7
Summary: A file-based document store with python interface
Keywords: document store,file-based,python,pydantic,sqlite
Author-email: Roman Right <roman-right@protonmail.com>
Requires-Python: >=3.8,<4.0
Requires-Dist: pydantic>=2.1
Requires-Dist: pre-commit>=2.3.0 ; extra == "test"
Requires-Dist: pytest>=6.0.0 ; extra == "test"
Requires-Dist: pytest-cov>=2.8.1 ; extra == "test"
Project-URL: repository, https://github.com/roman-right/bosc
Provides-Extra: test
